LICENSE
README.md
pyproject.toml
setup.py
Dev_Helper_CLI.egg-info/PKG-INFO
Dev_Helper_CLI.egg-info/SOURCES.txt
Dev_Helper_CLI.egg-info/dependency_links.txt
Dev_Helper_CLI.egg-info/entry_points.txt
Dev_Helper_CLI.egg-info/requires.txt
Dev_Helper_CLI.egg-info/top_level.txt
dh/__init__.py
dh/cli.py
dh/backend/__init__.py
dh/backend/document_db.py
dh/backend/validations.py