Metadata-Version: 2.1
Name: Dev-Helper-CLI
Version: 0.0.5
Summary: A CLI program to help devs be more productive.
Home-page: https://github.com/luigicfh/Dev-Helper-2.0
Author: Luis Moreno
Author-email: luis.cfh.90@gmail.com
Project-URL: Bug Tracker, https://github.com/luigicfh/Dev-Helper-2.0/issues
Classifier: Programming Language :: Python :: 3
Classifier: License :: OSI Approved :: MIT License
Classifier: Operating System :: OS Independent
Requires-Python: >=3.6
License-File: LICENSE
